{
 "eta": 1,
 "etat_eff": 127,
 "etar_eff": 44080.365,
 "brandt": 32.15165936619757,
 "brandr": 598.9962762438511,
 "N": 127,
 "theta_max": 1e+30,
 "print_skip": 200,
 "min_Nsteps": 1e+30,
 "avglen": 100,
 "omega_min": -1,
 "omega_max": 1e+30,
 "pos_cm": [
  0.0,
  0.0
 ],
 "angle": 0,
 "sigma": 0.5,
 "a": 0.6,
 "b": 2.0,
 "wd": 0.29,
 "dt": 0.0001,
 "epsilon": 105,
 "sub_symm": "square",
 "well_shape": "gaussian",
 "R": 5.0,
 "Nsteps": 300000,
 "cluster_hex": "input_hex-Nl_7.hex",
 "both_breaks": false,
 "T": 4.0698,
 "Tau": 35000.0,
 "Fx": 0.0,
 "Fy": 0.0
}